elabapi_python/__init__.py
elabapi_python/api_client.py
elabapi_python/configuration.py
elabapi_python/rest.py
elabapi_python/api/__init__.py
elabapi_python/api/api_keys_api.py
elabapi_python/api/comments_api.py
elabapi_python/api/compounds_api.py
elabapi_python/api/config_api.py
elabapi_python/api/events_api.py
elabapi_python/api/experiments_api.py
elabapi_python/api/experiments_categories_api.py
elabapi_python/api/experiments_status_api.py
elabapi_python/api/experiments_templates_api.py
elabapi_python/api/exports_api.py
elabapi_python/api/extra_fields_keys_api.py
elabapi_python/api/favorite_tags_api.py
elabapi_python/api/idps_api.py
elabapi_python/api/import_api.py
elabapi_python/api/info_api.py
elabapi_python/api/items_api.py
elabapi_python/api/items_types__resources_templates_api.py
elabapi_python/api/links_to_experiments_api.py
elabapi_python/api/links_to_items_api.py
elabapi_python/api/notifications_api.py
elabapi_python/api/reports_api.py
elabapi_python/api/resources_categories_api.py
elabapi_python/api/resources_status_api.py
elabapi_python/api/revisions_api.py
elabapi_python/api/steps_api.py
elabapi_python/api/tags_api.py
elabapi_python/api/team_tags_api.py
elabapi_python/api/teamgroups_api.py
elabapi_python/api/teams_api.py
elabapi_python/api/todolist_api.py
elabapi_python/api/unfinished_steps_api.py
elabapi_python/api/uploads_api.py
elabapi_python/api/user_uploads_api.py
elabapi_python/api/users_api.py
elabapi_python/models/__init__.py
elabapi_python/models/any_ofuploads_subid_body1.py
elabapi_python/models/apikey.py
elabapi_python/models/apikeys_body.py
elabapi_python/models/comment.py
elabapi_python/models/compound.py
elabapi_python/models/compound_create_request.py
elabapi_python/models/compound_duplicate_request.py
elabapi_python/models/compounds_body.py
elabapi_python/models/config.py
elabapi_python/models/entity.py
elabapi_python/models/entity_editable.py
elabapi_python/models/entity_template.py
elabapi_python/models/entity_template_editable.py
elabapi_python-5.3.1.dist-info/METADATA
elabapi_python-5.3.1.dist-info/WHEEL
elabapi_python-5.3.1.dist-info/top_level.txt
elabapi_python-5.3.1.dist-info/RECORD
