Metadata-Version: 2.4
Name: elabapi-python
Version: 5.3.1
Summary: eLabFTW REST API v2 Documentation
Home-page: https://github.com/elabftw/elabapi-python
Author-email: 
Keywords: Swagger,eLabFTW REST API v2 Documentation
Requires-Dist: urllib3>=1.15
Requires-Dist: six>=1.10
Requires-Dist: certifi
Requires-Dist: python-dateutil
Dynamic: description
Dynamic: home-page
Dynamic: keywords
Dynamic: requires-dist
Dynamic: summary
